{"chunk_definitions":[{"row":66,"row_count":1,"visible":true,"expansion_state":0,"options":{"engine":"r","label":"unnamed-chunk-2","dev":"png"},"document_id":"D24DB619","chunk_id":"cdzpupegt21h0","chunk_label":"unnamed-chunk-1"},{"row":87,"row_count":1,"visible":true,"expansion_state":0,"options":{"engine":"r","label":"unnamed-chunk-3","dev":"png"},"document_id":"D24DB619","chunk_id":"cyqg57723wwhn","chunk_label":"unnamed-chunk-2"},{"row":104,"row_count":1,"visible":true,"expansion_state":0,"options":{"engine":"r","label":"unnamed-chunk-4","dev":"png"},"document_id":"D24DB619","chunk_id":"c7y7qq86yazct","chunk_label":"unnamed-chunk-3"},{"row":125,"row_count":1,"visible":true,"expansion_state":0,"options":{"engine":"r","label":"unnamed-chunk-5","dev":"png"},"document_id":"D24DB619","chunk_id":"ccdrs25hdv9cc","chunk_label":"unnamed-chunk-4"},{"row":136,"row_count":1,"visible":true,"expansion_state":0,"options":{"engine":"r","label":"unnamed-chunk-6","dev":"png"},"document_id":"D24DB619","chunk_id":"cinpe8isay7e0","chunk_label":"unnamed-chunk-5"},{"row":149,"row_count":1,"visible":true,"expansion_state":0,"options":{"engine":"r","label":"unnamed-chunk-7","dev":"png"},"document_id":"D24DB619","chunk_id":"c1zvwb9t1tdpx","chunk_label":"unnamed-chunk-6"},{"row":162,"row_count":1,"visible":true,"expansion_state":0,"options":{"engine":"r","label":"unnamed-chunk-8","dev":"png"},"document_id":"D24DB619","chunk_id":"cvffv4a5fw5li","chunk_label":"unnamed-chunk-7"},{"row":188,"row_count":1,"visible":true,"expansion_state":0,"options":{"engine":"r","label":"unnamed-chunk-9","dev":"png"},"document_id":"D24DB619","chunk_id":"c5yjxl758vfd9","chunk_label":"unnamed-chunk-8"},{"row":200,"row_count":1,"visible":true,"expansion_state":0,"options":{"engine":"r","label":"unnamed-chunk-10","dev":"png"},"document_id":"D24DB619","chunk_id":"c9z64attm9lwi","chunk_label":"unnamed-chunk-9"},{"row":240,"row_count":1,"visible":true,"expansion_state":0,"options":{"engine":"r","label":"unnamed-chunk-11","dev":"png"},"document_id":"D24DB619","chunk_id":"cu496wxwqze64","chunk_label":"unnamed-chunk-10"},{"row":291,"row_count":1,"visible":true,"expansion_state":0,"options":{"engine":"r","label":"unnamed-chunk-12","dev":"png"},"document_id":"D24DB619","chunk_id":"cadbr7vbo1q01","chunk_label":"unnamed-chunk-11"},{"row":356,"row_count":1,"visible":true,"expansion_state":0,"options":{"engine":"r","label":"unnamed-chunk-13","dev":"png"},"document_id":"D24DB619","chunk_id":"c2b93r2zvk0jv","chunk_label":"unnamed-chunk-12"},{"row":390,"row_count":1,"visible":true,"expansion_state":0,"options":{"engine":"r","label":"unnamed-chunk-14","dev":"png"},"document_id":"D24DB619","chunk_id":"ckw3vphz37jki","chunk_label":"unnamed-chunk-13"},{"row":432,"row_count":1,"visible":true,"expansion_state":0,"options":{"engine":"r","label":"unnamed-chunk-17","dev":"png"},"document_id":"D24DB619","chunk_id":"c7ujkzg0b1w5n","chunk_label":"unnamed-chunk-14"},{"row":497,"row_count":1,"visible":true,"expansion_state":0,"options":{"engine":"r","label":"unnamed-chunk-18","dev":"png"},"document_id":"D24DB619","chunk_id":"c2wfqsfalxmzc","chunk_label":"unnamed-chunk-15"},{"row":548,"row_count":1,"visible":true,"expansion_state":0,"options":{"engine":"r","label":"unnamed-chunk-19","dev":"png"},"document_id":"D24DB619","chunk_id":"cwfsouxm2shht","chunk_label":"unnamed-chunk-16"},{"row":600,"row_count":1,"visible":true,"expansion_state":0,"options":{"engine":"r","label":"unnamed-chunk-20","dev":"png"},"document_id":"D24DB619","chunk_id":"cawwp2h4y7119","chunk_label":"unnamed-chunk-17"}],"doc_write_time":1733661660}